mappymatch/__about__.py
mappymatch/__init__.py
mappymatch/constructs/__init__.py
mappymatch/constructs/coordinate.py
mappymatch/constructs/geofence.py
mappymatch/constructs/match.py
mappymatch/constructs/road.py
mappymatch/constructs/trace.py
mappymatch/maps/__init__.py
mappymatch/maps/map_interface.py
mappymatch/maps/igraph/__init__.py
mappymatch/maps/igraph/igraph_map.py
mappymatch/maps/nx/__init__.py
mappymatch/maps/nx/nx_map.py
mappymatch/maps/nx/readers/__init__.py
mappymatch/maps/nx/readers/osm_readers.py
mappymatch/matchers/__init__.py
mappymatch/matchers/line_snap.py
mappymatch/matchers/match_result.py
mappymatch/matchers/matcher_interface.py
mappymatch/matchers/osrm.py
mappymatch/matchers/valhalla.py
mappymatch/matchers/lcss/__init__.py
mappymatch/matchers/lcss/constructs.py
mappymatch/matchers/lcss/lcss.py
mappymatch/matchers/lcss/ops.py
mappymatch/matchers/lcss/utils.py
mappymatch/resources/__init__.py
mappymatch/resources/traces/sample_trace_1.csv
mappymatch/resources/traces/sample_trace_2.csv
mappymatch/resources/traces/sample_trace_3.csv
mappymatch/utils/__init__.py
mappymatch/utils/crs.py
mappymatch/utils/exceptions.py
mappymatch/utils/geo.py
mappymatch/utils/keys.py
mappymatch/utils/process_trace.py
mappymatch/utils/url.py
mappymatch/utils/plot/__init__.py
mappymatch/utils/plot/geofence.py
mappymatch/utils/plot/map.py
mappymatch/utils/plot/matches.py
mappymatch/utils/plot/path.py
mappymatch/utils/plot/trace.py
mappymatch/utils/plot/trajectory_segment.py
mappymatch-0.7.1.dist-info/METADATA
mappymatch-0.7.1.dist-info/WHEEL
mappymatch-0.7.1.dist-info/licenses/LICENSE
mappymatch-0.7.1.dist-info/RECORD
