Metadata-Version: 2.4
Name: mappymatch
Version: 0.7.1
Summary: Pure python package for map-matching.
Project-URL: Homepage, https://github.com/NREL/mappymatch
Author: National Renewable Energy Laboratory
License: BSD 3-Clause License Copyright (c) 2022, Alliance for Sustainable Energy, LLC
License-File: LICENSE
Keywords: GPS,map,match
Classifier: Development Status :: 4 - Beta
Classifier: Intended Audience :: Science/Research
Classifier: License :: Other/Proprietary License
Classifier: Operating System :: OS Independent
Classifier: Programming Language :: Python
Classifier: Programming Language :: Python :: 3.10
Classifier: Programming Language :: Python :: 3.11
Classifier: Programming Language :: Python :: 3.12
Classifier: Programming Language :: Python :: 3.13
Classifier: Topic :: Scientific/Engineering
Requires-Python: >=3.10
Requires-Dist: folium<1,>=0.20
Requires-Dist: geopandas<2,>=1
Requires-Dist: igraph<2,>=1.0
Requires-Dist: matplotlib<4,>=3
Requires-Dist: networkx<4,>=3
Requires-Dist: numpy<3,>=2
Requires-Dist: osmnx<3,>=2
Requires-Dist: pandas<3,>=2
Requires-Dist: polyline<3,>=2
Requires-Dist: pyproj<4,>=3
Requires-Dist: requests<3,>=2
Requires-Dist: shapely<3,>=2
Provides-Extra: dev
Requires-Dist: coverage; extra == 'dev'
Requires-Dist: hatch<2,>=1; extra == 'dev'
Requires-Dist: jupyter-book>=2; extra == 'dev'
Requires-Dist: mypy<2,>=1; extra == 'dev'
Requires-Dist: pre-commit; extra == 'dev'
Requires-Dist: pytest<10,>=9; extra == 'dev'
Requires-Dist: ruff<1,>=0.14; extra == 'dev'
Requires-Dist: sphinx-autodoc-typehints; extra == 'dev'
Requires-Dist: sphinx-book-theme; extra == 'dev'
Requires-Dist: sphinxcontrib-autoyaml; extra == 'dev'
Requires-Dist: sphinxcontrib-mermaid; extra == 'dev'
Requires-Dist: types-requests; extra == 'dev'
Provides-Extra: docs
Requires-Dist: jupyter-book>=2; extra == 'docs'
Requires-Dist: sphinx-autodoc-typehints; extra == 'docs'
Requires-Dist: sphinx-book-theme; extra == 'docs'
Requires-Dist: sphinxcontrib-autoyaml; extra == 'docs'
Requires-Dist: sphinxcontrib-mermaid; extra == 'docs'
Provides-Extra: tests
Requires-Dist: mypy<2,>=1; extra == 'tests'
Requires-Dist: pytest<10,>=9; extra == 'tests'
Requires-Dist: ruff<1,>=0.14; extra == 'tests'
Requires-Dist: types-requests; extra == 'tests'
